hyperon_das/__init__.py
hyperon_das/cache/__init__.py
hyperon_das/cache/attention_broker_gateway.py
hyperon_das/cache/cache_controller.py
hyperon_das/cache/iterators.py
hyperon_das/client.py
hyperon_das/constants.py
hyperon_das/context.py
hyperon_das/das.py
hyperon_das/decorators.py
hyperon_das/exceptions.py
hyperon_das/grpc/attention_broker_pb2.py
hyperon_das/grpc/attention_broker_pb2.pyi
hyperon_das/grpc/attention_broker_pb2_grpc.py
hyperon_das/grpc/common_pb2.py
hyperon_das/grpc/common_pb2.pyi
hyperon_das/link_filters.py
hyperon_das/logger.py
hyperon_das/query_engines/local_query_engine.py
hyperon_das/query_engines/query_engine_protocol.py
hyperon_das/query_engines/remote_query_engine.py
hyperon_das/traverse_engines.py
hyperon_das/type_alias.py
hyperon_das/utils.py
site-packages/__init__.py
site-packages/_distutils_hack/__init__.py
site-packages/_distutils_hack/override.py
site-packages/async_timeout-5.0.1.dist-info/INSTALLER
site-packages/async_timeout-5.0.1.dist-info/LICENSE
site-packages/async_timeout-5.0.1.dist-info/METADATA
site-packages/async_timeout-5.0.1.dist-info/WHEEL
site-packages/async_timeout-5.0.1.dist-info/top_level.txt
site-packages/async_timeout-5.0.1.dist-info/zip-safe
site-packages/async_timeout/__init__.py
site-packages/async_timeout/py.typed
site-packages/bson/__init__.py
site-packages/bson/_cbson.cpython-310-x86_64-linux-gnu.so
site-packages/bson/_cbson.cpython-39-x86_64-linux-gnu.so
site-packages/bson/_cbsonmodule.c
site-packages/bson/_cbsonmodule.h
site-packages/bson/_helpers.py
site-packages/bson/binary.py
site-packages/bson/bson-endian.h
site-packages/bson/buffer.c
site-packages/bson/buffer.h
site-packages/bson/code.py
site-packages/bson/codec_options.py
site-packages/bson/datetime_ms.py
site-packages/bson/dbref.py
site-packages/bson/decimal128.py
site-packages/bson/errors.py
site-packages/bson/int64.py
site-packages/bson/json_util.py
site-packages/bson/max_key.py
site-packages/bson/min_key.py
site-packages/bson/objectid.py
site-packages/bson/py.typed
site-packages/bson/raw_bson.py
site-packages/bson/regex.py
site-packages/bson/son.py
site-packages/bson/time64.c
site-packages/bson/time64.h
site-packages/bson/time64_config.h
site-packages/bson/time64_limits.h
site-packages/bson/timestamp.py
site-packages/bson/typings.py
site-packages/bson/tz_util.py
site-packages/certifi-2025.1.31.dist-info/INSTALLER
site-packages/certifi-2025.1.31.dist-info/LICENSE
site-packages/certifi-2025.1.31.dist-info/METADATA
site-packages/certifi-2025.1.31.dist-info/WHEEL
site-packages/certifi-2025.1.31.dist-info/top_level.txt
site-packages/charset_normalizer-3.4.1.dist-info/INSTALLER
site-packages/charset_normalizer-3.4.1.dist-info/LICENSE
site-packages/charset_normalizer-3.4.1.dist-info/METADATA
site-packages/charset_normalizer-3.4.1.dist-info/WHEEL
site-packages/charset_normalizer-3.4.1.dist-info/entry_points.txt
site-packages/charset_normalizer-3.4.1.dist-info/top_level.txt
site-packages/dnspython-2.7.0.dist-info/INSTALLER
site-packages/dnspython-2.7.0.dist-info/METADATA
site-packages/dnspython-2.7.0.dist-info/WHEEL
site-packages/dnspython-2.7.0.dist-info/licenses/LICENSE
site-packages/grpcio-1.71.0.dist-info/INSTALLER
site-packages/grpcio-1.71.0.dist-info/LICENSE
site-packages/grpcio-1.71.0.dist-info/METADATA
site-packages/grpcio-1.71.0.dist-info/WHEEL
site-packages/grpcio-1.71.0.dist-info/top_level.txt
site-packages/hyperon_das_atomdb-0.8.10.dist-info/INSTALLER
site-packages/hyperon_das_atomdb-0.8.10.dist-info/LICENCE
site-packages/hyperon_das_atomdb-0.8.10.dist-info/METADATA
site-packages/hyperon_das_atomdb-0.8.10.dist-info/WHEEL
site-packages/hyperon_das_atomdb_cpp-0.0.2.dist-info/INSTALLER
site-packages/hyperon_das_atomdb_cpp-0.0.2.dist-info/METADATA
site-packages/hyperon_das_atomdb_cpp-0.0.2.dist-info/WHEEL
site-packages/idna-3.10.dist-info/INSTALLER
site-packages/idna-3.10.dist-info/LICENSE.md
site-packages/idna-3.10.dist-info/METADATA
site-packages/idna-3.10.dist-info/WHEEL
site-packages/mongomock-4.3.0.dist-info/INSTALLER
site-packages/mongomock-4.3.0.dist-info/METADATA
site-packages/mongomock-4.3.0.dist-info/WHEEL
site-packages/mongomock-4.3.0.dist-info/licenses/LICENSE
site-packages/packaging-24.2.dist-info/INSTALLER
site-packages/packaging-24.2.dist-info/LICENSE
site-packages/packaging-24.2.dist-info/LICENSE.APACHE
site-packages/packaging-24.2.dist-info/LICENSE.BSD
site-packages/packaging-24.2.dist-info/METADATA
site-packages/packaging-24.2.dist-info/WHEEL
site-packages/protobuf-4.25.6.dist-info/INSTALLER
site-packages/protobuf-4.25.6.dist-info/LICENSE
site-packages/protobuf-4.25.6.dist-info/METADATA
site-packages/protobuf-4.25.6.dist-info/WHEEL
site-packages/pymongo-4.12.0.dist-info/INSTALLER
site-packages/pymongo-4.12.0.dist-info/METADATA
site-packages/pymongo-4.12.0.dist-info/WHEEL
site-packages/pymongo-4.12.0.dist-info/licenses/LICENSE
site-packages/python_dotenv-1.1.0.dist-info/INSTALLER
site-packages/python_dotenv-1.1.0.dist-info/METADATA
site-packages/python_dotenv-1.1.0.dist-info/WHEEL
site-packages/python_dotenv-1.1.0.dist-info/entry_points.txt
site-packages/python_dotenv-1.1.0.dist-info/licenses/LICENSE
site-packages/python_dotenv-1.1.0.dist-info/top_level.txt
site-packages/pytz-2025.2.dist-info/INSTALLER
site-packages/pytz-2025.2.dist-info/LICENSE.txt
site-packages/pytz-2025.2.dist-info/METADATA
site-packages/pytz-2025.2.dist-info/WHEEL
site-packages/pytz-2025.2.dist-info/top_level.txt
site-packages/pytz-2025.2.dist-info/zip-safe
site-packages/redis-5.2.1.dist-info/INSTALLER
site-packages/redis-5.2.1.dist-info/LICENSE
site-packages/redis-5.2.1.dist-info/METADATA
site-packages/redis-5.2.1.dist-info/WHEEL
site-packages/redis-5.2.1.dist-info/top_level.txt
site-packages/requests-2.32.3.dist-info/INSTALLER
site-packages/requests-2.32.3.dist-info/LICENSE
site-packages/requests-2.32.3.dist-info/METADATA
site-packages/requests-2.32.3.dist-info/WHEEL
site-packages/requests-2.32.3.dist-info/top_level.txt
site-packages/sentinels-1.0.0.dist-info/INSTALLER
