Metadata-Version: 2.1
Name: hyperon_das
Author: Andre Senna
Author-email: andre@singularitynet.io
Summary: Query Engine API for Distributed AtomSpace
Classifier: Programming Language :: Python :: 3
Classifier: Programming Language :: Python :: 3.10
Classifier: Programming Language :: Python :: 3.11
Classifier: Programming Language :: Python :: 3.12
Classifier: Programming Language :: Python :: 3.13
Requires-Python: >=3.10
Requires-Dist: async-timeout==5.0.1
Requires-Dist: beautifulsoup4==4.13.3
Requires-Dist: certifi==2025.1.31
Requires-Dist: charset-normalizer==3.4.1
Requires-Dist: dnspython==2.7.0
Requires-Dist: google==3.0.0
Requires-Dist: grpcio==1.71.0
Requires-Dist: hyperon-das-atomdb==0.8.10
Requires-Dist: hyperon-das-atomdb-cpp==0.0.2
Requires-Dist: idna==3.10
Requires-Dist: mongomock==4.3.0
Requires-Dist: packaging==24.2
Requires-Dist: protobuf==4.25.6
Requires-Dist: pymongo==4.12.0
Requires-Dist: python-dotenv==1.1.0
Requires-Dist: pytz==2025.2
Requires-Dist: redis==5.2.1
Requires-Dist: requests==2.32.3
Requires-Dist: sentinels==1.0.0
Requires-Dist: soupsieve==2.6
Requires-Dist: typing-extensions==4.13.1
Requires-Dist: urllib3==2.3.0
Requires-Dist: setuptools==70.3.0
Version: 0.10.1
